wxcompose/__init__.py
wxcompose/binding.py
wxcompose/component.py
wxcompose/core.py
wxcompose/viewmodel.py
wxcompose-1.1.0.dist-info/licenses/LICENSE
wxcompose-1.1.0.dist-info/METADATA
wxcompose-1.1.0.dist-info/WHEEL
wxcompose-1.1.0.dist-info/top_level.txt
wxcompose-1.1.0.dist-info/RECORD
